[
  {
    "position": 1,
    "positionText": "1",
    "points": 25,
    "driverId": "max_verstappen",
    "constructorId": "red_bull",
    "grid": 2,
    "laps": 70,
    "status": "Finished",
    "time": "1:45:47.927",
    "fastestLapRank": 4,
    "fastestLapNumber": 70,
    "fastestLapTime": "1:15.569"
  },
  {
    "position": 2,
    "positionText": "2",
    "points": 18,
    "driverId": "norris",
    "constructorId": "mclaren",
    "grid": 3,
    "laps": 70,
    "status": "Finished",
    "time": "+3.879",
    "fastestLapRank": 3,
    "fastestLapNumber": 67,
    "fastestLapTime": "1:15.558"
  },
  {
    "position": 3,
    "positionText": "3",
    "points": 15,
    "driverId": "russell",
    "constructorId": "mercedes",
    "grid": 1,
    "laps": 70,
    "status": "Finished",
    "time": "+4.317",
    "fastestLapRank": 2,
    "fastestLapNumber": 70,
    "fastestLapTime": "1:14.895"
  },
  {
    "position": 4,
    "positionText": "4",
    "points": 13,
    "driverId": "hamilton",
    "constructorId": "mercedes",
    "grid": 7,
    "laps": 70,
    "status": "Finished",
    "time": "+4.915",
    "fastestLapRank": 1,
    "fastestLapNumber": 70,
    "fastestLapTime": "1:14.856"
  },
  {
    "position": 5,
    "positionText": "5",
    "points": 10,
    "driverId": "piastri",
    "constructorId": "mclaren",
    "grid": 4,
    "laps": 70,
    "status": "Finished",
    "time": "+10.199",
    "fastestLapRank": 5,
    "fastestLapNumber": 65,
    "fastestLapTime": "1:16.247"
  },
  {
    "position": 6,
    "positionText": "6",
    "points": 8,
    "driverId": "alonso",
    "constructorId": "aston_martin",
    "grid": 6,
    "laps": 70,
    "status": "Finished",
    "time": "+17.510",
    "fastestLapRank": 6,
    "fastestLapNumber": 70,
    "fastestLapTime": "1:16.303"
  },
  {
    "position": 7,
    "positionText": "7",
    "points": 6,
    "driverId": "stroll",
    "constructorId": "aston_martin",
    "grid": 9,
    "laps": 70,
    "status": "Finished",
    "time": "+23.625",
    "fastestLapRank": 9,
    "fastestLapNumber": 70,
    "fastestLapTime": "1:16.762"
  },
  {
    "position": 8,
    "positionText": "8",
    "points": 4,
    "driverId": "ricciardo",
    "constructorId": "rb",
    "grid": 5,
    "laps": 70,
    "status": "Finished",
    "time": "+28.672",
    "fastestLapRank": 12,
    "fastestLapNumber": 68,
    "fastestLapTime": "1:17.076"
  },
  {
    "position": 9,
    "positionText": "9",
    "points": 2,
    "driverId": "gasly",
    "constructorId": "alpine",
    "grid": 15,
    "laps": 70,
    "status": "Finished",
    "time": "+30.021",
    "fastestLapRank": 11,
    "fastestLapNumber": 70,
    "fastestLapTime": "1:17.013"
  },
  {
    "position": 10,
    "positionText": "10",
    "points": 1,
    "driverId": "ocon",
    "constructorId": "alpine",
    "grid": 18,
    "laps": 70,
    "status": "Finished",
    "time": "+30.313",
    "fastestLapRank": 10,
    "fastestLapNumber": 70,
    "fastestLapTime": "1:17.012"
  },
  {
    "position": 11,
    "positionText": "11",
    "points": 0,
    "driverId": "hulkenberg",
    "constructorId": "haas",
    "grid": 17,
    "laps": 70,
    "status": "Finished",
    "time": "+30.824",
    "fastestLapRank": 8,
    "fastestLapNumber": 67,
    "fastestLapTime": "1:16.683"
  },
  {
    "position": 12,
    "positionText": "12",
    "points": 0,
    "driverId": "kevin_magnussen",
    "constructorId": "haas",
    "grid": 14,
    "laps": 70,
    "status": "Finished",
    "time": "+31.253",
    "fastestLapRank": 7,
    "fastestLapNumber": 68,
    "fastestLapTime": "1:16.499"
  },
  {
    "position": 13,
    "positionText": "13",
    "points": 0,
    "driverId": "bottas",
    "constructorId": "sauber",
    "grid": 19,
    "laps": 70,
    "status": "Finished",
    "time": "+40.487",
    "fastestLapRank": 13,
    "fastestLapNumber": 65,
    "fastestLapTime": "1:17.250"
  },
  {
    "position": 14,
    "positionText": "14",
    "points": 0,
    "driverId": "tsunoda",
    "constructorId": "rb",
    "grid": 8,
    "laps": 70,
    "status": "Finished",
    "time": "+52.694",
    "fastestLapRank": 14,
    "fastestLapNumber": 70,
    "fastestLapTime": "1:17.309"
  },
  {
    "position": 15,
    "positionText": "15",
    "points": 0,
    "driverId": "zhou",
    "constructorId": "sauber",
    "grid": 20,
    "laps": 69,
    "status": "Lapped",
    "time": "+53.528",
    "fastestLapRank": 15,
    "fastestLapNumber": 68,
    "fastestLapTime": "1:17.325"
  },
  {
    "position": null,
    "positionText": "R",
    "points": 0,
    "driverId": "sainz",
    "constructorId": "ferrari",
    "grid": 12,
    "laps": 52,
    "status": "Retired",
    "time": null,
    "fastestLapRank": 17,
    "fastestLapNumber": 51,
    "fastestLapTime": "1:18.957"
  },
  {
    "position": null,
    "positionText": "R",
    "points": 0,
    "driverId": "albon",
    "constructorId": "williams",
    "grid": 10,
    "laps": 52,
    "status": "Retired",
    "time": null,
    "fastestLapRank": 18,
    "fastestLapNumber": 51,
    "fastestLapTime": "1:19.359"
  },
  {
    "position": null,
    "positionText": "R",
    "points": 0,
    "driverId": "perez",
    "constructorId": "red_bull",
    "grid": 16,
    "laps": 51,
    "status": "Retired",
    "time": null,
    "fastestLapRank": 16,
    "fastestLapNumber": 51,
    "fastestLapTime": "1:18.819"
  },
  {
    "position": null,
    "positionText": "R",
    "points": 0,
    "driverId": "leclerc",
    "constructorId": "ferrari",
    "grid": 11,
    "laps": 40,
    "status": "Retired",
    "time": null,
    "fastestLapRank": 19,
    "fastestLapNumber": 39,
    "fastestLapTime": "1:26.012"
  },
  {
    "position": null,
    "positionText": "R",
    "points": 0,
    "driverId": "sargeant",
    "constructorId": "williams",
    "grid": 13,
    "laps": 23,
    "status": "Retired",
    "time": null,
    "fastestLapRank": 20,
    "fastestLapNumber": 19,
    "fastestLapTime": "1:26.484"
  }
]
