[
  {
    "year": 1988,
    "round": 1,
    "name": "Brazilian Grand Prix",
    "date": "1988-04-03",
    "time": null,
    "circuitId": "jacarepagua",
    "url": "https://en.wikipedia.org/wiki/1988_Brazilian_Grand_Prix"
  },
  {
    "year": 1988,
    "round": 2,
    "name": "San Marino Grand Prix",
    "date": "1988-05-01",
    "time": null,
    "circuitId": "imola",
    "url": "https://en.wikipedia.org/wiki/1988_San_Marino_Grand_Prix"
  },
  {
    "year": 1988,
    "round": 3,
    "name": "Monaco Grand Prix",
    "date": "1988-05-15",
    "time": null,
    "circuitId": "monaco",
    "url": "https://en.wikipedia.org/wiki/1988_Monaco_Grand_Prix"
  },
  {
    "year": 1988,
    "round": 4,
    "name": "Mexican Grand Prix",
    "date": "1988-05-29",
    "time": null,
    "circuitId": "rodriguez",
    "url": "https://en.wikipedia.org/wiki/1988_Mexican_Grand_Prix"
  },
  {
    "year": 1988,
    "round": 5,
    "name": "Canadian Grand Prix",
    "date": "1988-06-12",
    "time": null,
    "circuitId": "villeneuve",
    "url": "https://en.wikipedia.org/wiki/1988_Canadian_Grand_Prix"
  },
  {
    "year": 1988,
    "round": 6,
    "name": "Detroit Grand Prix",
    "date": "1988-06-19",
    "time": null,
    "circuitId": "detroit",
    "url": "https://en.wikipedia.org/wiki/1988_Detroit_Grand_Prix"
  },
  {
    "year": 1988,
    "round": 7,
    "name": "French Grand Prix",
    "date": "1988-07-03",
    "time": null,
    "circuitId": "ricard",
    "url": "https://en.wikipedia.org/wiki/1988_French_Grand_Prix"
  },
  {
    "year": 1988,
    "round": 8,
    "name": "British Grand Prix",
    "date": "1988-07-10",
    "time": null,
    "circuitId": "silverstone",
    "url": "https://en.wikipedia.org/wiki/1988_British_Grand_Prix"
  },
  {
    "year": 1988,
    "round": 9,
    "name": "German Grand Prix",
    "date": "1988-07-24",
    "time": null,
    "circuitId": "hockenheimring",
    "url": "https://en.wikipedia.org/wiki/1988_German_Grand_Prix"
  },
  {
    "year": 1988,
    "round": 10,
    "name": "Hungarian Grand Prix",
    "date": "1988-08-07",
    "time": null,
    "circuitId": "hungaroring",
    "url": "https://en.wikipedia.org/wiki/1988_Hungarian_Grand_Prix"
  },
  {
    "year": 1988,
    "round": 11,
    "name": "Belgian Grand Prix",
    "date": "1988-08-28",
    "time": null,
    "circuitId": "spa",
    "url": "https://en.wikipedia.org/wiki/1988_Belgian_Grand_Prix"
  },
  {
    "year": 1988,
    "round": 12,
    "name": "Italian Grand Prix",
    "date": "1988-09-11",
    "time": null,
    "circuitId": "monza",
    "url": "https://en.wikipedia.org/wiki/1988_Italian_Grand_Prix"
  },
  {
    "year": 1988,
    "round": 13,
    "name": "Portuguese Grand Prix",
    "date": "1988-09-25",
    "time": null,
    "circuitId": "estoril",
    "url": "https://en.wikipedia.org/wiki/1988_Portuguese_Grand_Prix"
  },
  {
    "year": 1988,
    "round": 14,
    "name": "Spanish Grand Prix",
    "date": "1988-10-02",
    "time": null,
    "circuitId": "jerez",
    "url": "https://en.wikipedia.org/wiki/1988_Spanish_Grand_Prix"
  },
  {
    "year": 1988,
    "round": 15,
    "name": "Japanese Grand Prix",
    "date": "1988-10-30",
    "time": null,
    "circuitId": "suzuka",
    "url": "https://en.wikipedia.org/wiki/1988_Japanese_Grand_Prix"
  },
  {
    "year": 1988,
    "round": 16,
    "name": "Australian Grand Prix",
    "date": "1988-11-13",
    "time": null,
    "circuitId": "adelaide",
    "url": "https://en.wikipedia.org/wiki/1988_Australian_Grand_Prix"
  }
]
